cie/cie10.py
cie/data/cie-10.zip
cie10_django/__init__.py
cie10_django/admin.py
cie10_django/apps.py
cie10_django/models.py
cie10_django/tests.py
cie10_django/views.py
cie10_django/migrations/0001_initial.py
cie10_django/migrations/__init__.py
cie-0.208.dist-info/METADATA
cie-0.208.dist-info/WHEEL
cie-0.208.dist-info/top_level.txt
cie-0.208.dist-info/RECORD
