Metadata-Version: 2.1
Name: cie
Version: 0.208
Summary: Lista de Códigos CIE10 en español como librería python simple o para uso dentro de django como app
Home-page: https://github.com/cluster311/cie10
Author: Andrés Vazquez
Author-email: andres@data99.com.ar
License: MIT
Platform: UNKNOWN
Classifier: Programming Language :: Python :: 3
Classifier: Programming Language :: Python :: 3.6
Classifier: License :: OSI Approved :: MIT License
Classifier: Operating System :: OS Independent
Classifier: Intended Audience :: Developers
Classifier: Framework :: Django
Classifier: Framework :: Django :: 2.2
Requires-Python: >=3.6
Provides-Extra: django
Requires-Dist: Django (>=1.11) ; extra == 'django'
